napari_sentinel_zip/__init__.py
napari_sentinel_zip/napari_sentinel_zip.py
napari_sentinel_zip/_tests/__init__.py
napari_sentinel_zip/_tests/test_loading.py
napari_sentinel_zip/_tests/test_napari_sentinel_zip.py
napari_sentinel_zip-0.2.2.dist-info/LICENSE
napari_sentinel_zip-0.2.2.dist-info/METADATA
napari_sentinel_zip-0.2.2.dist-info/WHEEL
napari_sentinel_zip-0.2.2.dist-info/entry_points.txt
napari_sentinel_zip-0.2.2.dist-info/top_level.txt
napari_sentinel_zip-0.2.2.dist-info/RECORD
