Metadata-Version: 2.1
Name: napari-sentinel-zip
Version: 0.2.2
Summary: Stacks and opens Sentinel mission zip archives for one tile across different timepoints.
Home-page: https://github.com/DragaDoncila/napari-sentinel-zip
Author: Draga Doncila Pop
Author-email: ddon0001@student.monash.edu
License: MIT
Platform: UNKNOWN
Classifier: Development Status :: 4 - Beta
Classifier: Intended Audience :: Developers
Classifier: Topic :: Software Development :: Testing
Classifier: Programming Language :: Python
Classifier: Programming Language :: Python :: 3
Classifier: Programming Language :: Python :: 3.6
Classifier: Programming Language :: Python :: 3.7
Classifier: Programming Language :: Python :: 3.8
Classifier: Programming Language :: Python :: Implementation :: CPython
Classifier: Programming Language :: Python :: Implementation :: PyPy
Classifier: Operating System :: OS Independent
Classifier: License :: OSI Approved :: MIT License
Requires-Python: >=3.6
Requires-Dist: napari-plugin-engine (>=0.1.4)
Requires-Dist: numpy
Requires-Dist: tifffile
Requires-Dist: dask[array]
Requires-Dist: scikit-image
Requires-Dist: napari[all]
